[
  {
    "results": [
      {
        "final": true,
        "alternatives": [
          {
            "transcript": "most homeowners would prefer grass to a lawn full of wheat forensic scientist weeds can tell a story ",
            "confidence": 0.77
          }
        ]
      },
      {
        "final": true,
        "alternatives": [
          {
            "transcript": "with the help of a plant biologist and a new high tech computer program investigators solve the mystery of the young girl's murder ",
            "confidence": 0.9
          }
        ]
      },
      {
        "final": true,
        "alternatives": [
          {
            "transcript": "this ",
            "confidence": 0.26
          }
        ]
      },
      {
        "final": true,
        "alternatives": [
          {
            "transcript": "weekends were typically busy in the Mauser household ",
            "confidence": 0.67
          }
        ]
      },
      {
        "final": true,
        "alternatives": [
          {
            "transcript": "1 Saturday morning in 1995 as Cassie Mauser was leaving for work she reminded her 14 year old daughter Jenna she was grounded for the weekend and wasn't allowed to use the telephone either Janet was having some behavioral issues a lot of 14 year old 15 year olds might have those kinds of issues when they're growing up lots of pressure social pressures and problems within the family she was having such trouble that the family was taking her to counseling ",
            "confidence": 0.9
          }
        ]
      },
      {
        "final": true,
        "alternatives": [
          {
            "transcript": "he returned home from work around 1:00 PM and as soon as she tried to open the door she knew something was wrong ",
            "confidence": 0.92
          }
        ]
      },
      {
        "final": true,
        "alternatives": [
          {
            "transcript": "this is not a found the front door locks which she said was unusual because usually there isn't there somebody there she was expecting Jenner to be there so the front or what about a lot ",
            "confidence": 0.74
          }
        ]
      },
      {
        "final": true,
        "alternatives": [
          {
            "transcript": "Jennifer wasn't home and she had left a note saying where she went they just figured she was upset and she would basically just walked away ",
            "confidence": 0.81
          },
          {
            "transcript": "Jennifer wasn't home but she hadn't left a note saying where she went they just figured she was upset and she would basically just walked away "
          }
        ]
      },
      {
        "final": true,
        "alternatives": [
          {
            "transcript": "she was just with one of our friends are ",
            "confidence": 0.82
          }
        ]
      },
      {
        "final": true,
        "alternatives": [
          {
            "transcript": "yeah none of the neighbors saw Jenna leave or noticed anything suspicious ",
            "confidence": 0.85
          }
        ]
      },
      {
        "final": true,
        "alternatives": [
          {
            "transcript": "when John is stepfather and brother arrived home several hours later they search the neighborhood and call all her friends ",
            "confidence": 0.78
          }
        ]
      },
      {
        "final": true,
        "alternatives": [
          {
            "transcript": "no one knew where Jenna was ",
            "confidence": 0.66
          }
        ]
      },
      {
        "final": true,
        "alternatives": [
          {
            "transcript": "later that night the Moses called police to report their daughter missing ",
            "confidence": 0.86
          }
        ]
      },
      {
        "final": true,
        "alternatives": [
          {
            "transcript": "the next morning the monsters learned to nude body of a teenage girl was discovered in a ditch about 20 miles outside of town ",
            "confidence": 0.83
          }
        ]
      },
      {
        "final": true,
        "alternatives": [
          {
            "transcript": "the family identified Jenna's body at the morgue ",
            "confidence": 0.89
          }
        ]
      },
      {
        "final": true,
        "alternatives": [
          {
            "transcript": "the reality of her being murdered rather than an accident or it didn't hit me I didn't understand really that that something like that could happen in my life ",
            "confidence": 0.93
          }
        ]
      },
      {
        "final": true,
        "alternatives": [
          {
            "transcript": "it was it was hard to deal with and and to just such an unfair act ",
            "confidence": 0.87
          }
        ]
      },
      {
        "final": true,
        "alternatives": [
          {
            "transcript": "and I couldn't couldn't understand it for a long time ",
            "confidence": 0.89
          }
        ]
      },
      {
        "final": true,
        "alternatives": [
          {
            "transcript": "the coroner identified the cause of death as strangulation there were other injuries as well in addition to the ligature strangulation marks she also had evidence of blunt force injury to the head she had received a blow to the head and the left for head area and the left temple there were no defensive wounds and no signs of sexual assault ",
            "confidence": 0.96
          }
        ]
      },
      {
        "final": true,
        "alternatives": [
          {
            "transcript": "brown about 14 inches in length well the soles of the feet were a claim in this case and that indicates to me that she she certainly was not standing up at the scene where she was found she certainly did not walk there ",
            "confidence": 0.89
          }
        ]
      },
      {
        "final": true,
        "alternatives": [
          {
            "transcript": "the only other findings with some unusual marks on Jenner's 5 indentations that were made after death ",
            "confidence": 0.84
          }
        ]
      },
      {
        "final": true,
        "alternatives": [
          {
            "transcript": "on a living person these fade very quickly yeah in this case these are postmortem pressure marks they don't tend to fade because the the color, says the blood leaks out of the vessels by gravity after death and it more or less outlines the area of pressure and then it stays that way indefinitely until the body decomposes the monsters telephone records yielded the first clue ",
            "confidence": 0.87
          }
        ]
      },
      {
        "final": true,
        "alternatives": [
          {
            "transcript": "despite the fact Jenna was told not to use the telephone she called several friends that morning yeah you should talk to really is here we'll see a Monday around 1130 Jenness conversation with a friend ended abruptly hello ",
            "confidence": 0.9
          }
        ]
      },
      {
        "final": true,
        "alternatives": [
          {
            "transcript": "Jenna ",
            "confidence": 0.46
          }
        ]
      },
      {
        "final": true,
        "alternatives": [
          {
            "transcript": "Jena one of the last people that she speaks with says that the phone goes dead Janet is the call back the front pages for a couple of times China never calls ",
            "confidence": 0.77
          }
        ]
      },
      {
        "final": true,
        "alternatives": [
          {
            "transcript": "police found Jenna's diary in her bedroom which had an entry from the morning of her merger ",
            "confidence": 0.79
          }
        ]
      },
      {
        "final": true,
        "alternatives": [
          {
            "transcript": "sorry haven't you but I've been pretty busy things have been going pretty good at school except for the fact that guys don't even know I'm alive half the time ",
            "confidence": 0.88
          }
        ]
      },
      {
        "final": true,
        "alternatives": [
          {
            "transcript": "the diary expressed a specific interest in 2 boys one was considerably older than Jenna a boy she met at a local amusement park he was a young man about 18 or 19 years old who was ",
            "confidence": 0.9
          }
        ]
      },
      {
        "final": true,
        "alternatives": [
          {
            "transcript": " ",
            "confidence": 0.93
          }
        ]
      },
      {
        "final": true,
        "alternatives": [
          {
            "transcript": "children that were not age appropriate ",
            "confidence": 0.91
          }
        ]
      },
      {
        "final": true,
        "alternatives": [
          {
            "transcript": "he was older than us not not the best kind of person that you'd probably want to want to be with but he ",
            "confidence": 0.81
          }
        ]
      },
      {
        "final": true,
        "alternatives": [
          {
            "transcript": "there is something that she saw in him that attracted her to him ",
            "confidence": 0.87
          }
        ]
      },
      {
        "final": true,
        "alternatives": [
          {
            "transcript": "investigators needed to start checking alibis and there was one that almost defy belief ",
            "confidence": 0.81
          }
        ]
      },
      {
        "final": true,
        "alternatives": [
          {
            "transcript": "the most your family had planned a traditional funeral service for their 14 year old daughter Jenna ",
            "confidence": 0.91
          }
        ]
      },
      {
        "final": true,
        "alternatives": [
          {
            "transcript": "until her friend Sarah Hollander told them about a conversation the 2 once had about funerals we got on the topic as funerals and she did not want her funeral to be a sad thing she doesn't like it when people are sad she loves to make people happy so as to make people laugh and she definitely did not want her funeral to to portray something that she wasn't about to the Mauser is allowed Sara to help plan the funeral service one that was closer to Jenna's wishes ",
            "confidence": 0.85
          }
        ]
      },
      {
        "final": true,
        "alternatives": [
          {
            "transcript": "Mauser took his stepdaughter's death particularly hard he had raised Jenna said she was 2 years old and treated her like his own ",
            "confidence": 0.77
          }
        ]
      },
      {
        "final": true,
        "alternatives": [
          {
            "transcript": "she truly did have a great relationship with him and and loved him and he loved her he was very active in her life ",
            "confidence": 0.79
          }
        ]
      },
      {
        "final": true,
        "alternatives": [
          {
            "transcript": "in the search for Janice killer investigators looked inside the Mausers home but found no clues everything was basically in its place nothing knocked over or anything to indicate that a journalist fighting and screaming issue what went out the door this raised the possibility that Jenna left home voluntarily ",
            "confidence": 0.78
          }
        ]
      },
      {
        "final": true,
        "alternatives": [
          {
            "transcript": "with the sheriff's department did was try and identify any boys she might have known or or maybe if but she might have left the house with even though she was grounded maybe she'd get a car with him and drive away police were able to identify the 2 boys Jenna mentioned in her diary both had alibis for the day of the murder ",
            "confidence": 0.82
          }
        ]
      },
      {
        "final": true,
        "alternatives": [
          {
            "transcript": "so police turned their attention to the whereabouts of Janice family members ",
            "confidence": 0.81
          }
        ]
      },
      {
        "final": true,
        "alternatives": [
          {
            "transcript": "Jenness 18 year old brother Jeron had a solid alibi neighbors have him placed there for our hour point 5 or so and that's the time grade Regina disappears Jenna's mother Kathy was teaching an aerobics class at the local gym so her alibi checked out to ",
            "confidence": 0.85
          }
        ]
      },
      {
        "final": true,
        "alternatives": [
          {
            "transcript": "Jenness stepfather Doug said he went to work for a few hours when police tried to verify his alibi they discovered the security cameras at Doug's office were turned off that day when he went into the lab he's got to go through a security gate or all the cars that are coming in cleared ",
            "confidence": 0.88
          }
        ]
      },
      {
        "final": true,
        "alternatives": [
          {
            "transcript": "initially the person who was in the booth at the time said they didn't remember seeing cameras car come through that matter could give no description of the security guard and for a man who'd worked at the lab for a number of years you would think you would know the security guards remember them be able to give some description he could not so Doug provided a second alibi that he bought lunch at a local fast food restaurant coincidentally ",
            "confidence": 0.83
          }
        ]
      },
      {
        "final": true,
        "alternatives": [
          {
            "transcript": "the restaurants security cameras weren't working either ",
            "confidence": 0.81
          }
        ]
      },
      {
        "final": true,
        "alternatives": [
          {
            "transcript": "if you didn't have bad luck he would have no luck ",
            "confidence": 0.76
          }
        ]
      },
      {
        "final": true,
        "alternatives": [
          {
            "transcript": "I can't really imagine ",
            "confidence": 0.97
          }
        ]
      },
      {
        "final": true,
        "alternatives": [
          {
            "transcript": "you're going into places that are supposed to have video cameras and none of them record ",
            "confidence": 0.84
          }
        ]
      },
      {
        "final": true,
        "alternatives": [
          {
            "transcript": "M. sort exasperating because our snafus if you will you know we don't have any tapes we don't have any solid stuff to show that he was there ",
            "confidence": 0.79
          }
        ]
      },
      {
        "final": true,
        "alternatives": [
          {
            "transcript": "when police looked in Doug's car they found no blood or any evidence suggesting foul play and there was no evidence the car had recently been cleaned ",
            "confidence": 0.9
          }
        ]
      },
      {
        "final": true,
        "alternatives": [
          {
            "transcript": "but underneath the car ",
            "confidence": 0.89
          }
        ]
      },
      {
        "final": true,
        "alternatives": [
          {
            "transcript": "investigators found something trapped in the under carriage there is a significant quantity of these dried plant material some of it very large pieces I and those were removed hi and analyze later but ",
            "confidence": 0.84
          }
        ]
      },
      {
        "final": true,
        "alternatives": [
          {
            "transcript": "I had this plant material been there for weeks you certainly would expect to find such a large pieces of it still attached to the undercarriage ",
            "confidence": 0.89
          }
        ]
      },
      {
        "final": true,
        "alternatives": [
          {
            "transcript": "could these dried weeds tell investigators anything about Janice merger ",
            "confidence": 0.76
          }
        ]
      },
      {
        "final": true,
        "alternatives": [
          {
            "transcript": "Doug Mauser told police he was the last person to leave the house on the morning his step daughter went missing ",
            "confidence": 0.88
          }
        ]
      },
      {
        "final": true,
        "alternatives": [
          {
            "transcript": "he claimed Janet was cleaning her bedroom when he left there was no physical evidence that linked him you know like hair samples or DNA or anything like that there were no physical evidence ",
            "confidence": 0.89
          }
        ]
      },
      {
        "final": true,
        "alternatives": [
          {
            "transcript": "none there was a Zippo 0 nil nada nothing yet investigators found some suspicious plant material underneath dogs car which they sent to forensic botanist Dr Fred Rocha he identified the usual specimens you'd expect to find underneath the car grass dirt and debris ",
            "confidence": 0.9
          }
        ]
      },
      {
        "final": true,
        "alternatives": [
          {
            "transcript": "but he also found large quantities of yellow star thistle a week I saw the yellow star thistle and then I saw the small scraps that had been taken off the body and I was able to compare that to material that had been collected from the area around the body and also from the trees that were in the over story above the canyon where the body was found ",
            "confidence": 0.95
          }
        ]
      },
      {
        "final": true,
        "alternatives": [
          {
            "transcript": "Dr Rocha was looking for what botanists call diagnostic characteristics unique aspects of the plant the differentiated from others of the same species every plant has a life cycle in the life sequence early in the season they look different than they do late in the season and prior to death plant materials all species go through a sequence of developmental events ",
            "confidence": 0.88
          }
        ]
      },
      {
        "final": true,
        "alternatives": [
          {
            "transcript": "Dr Rusia discovered the star this'll under diagnosis Kerr was identical in development to the star thistle found near Janice body ",
            "confidence": 0.72
          }
        ]
      },
      {
        "final": true,
        "alternatives": [
          {
            "transcript": "while this was significant it wasn't enough to tie dyed Mauser to the murder yellow star thistle is not a rare plant is an extremely common plants so in any given area of specially in northern California you in the lower elevations a yellow star thistle could be there you can show that the evidence that was found underneath his car came from the crime scene it's true common in California and that with the other floor under the car it shows that he's been off road ",
            "confidence": 0.8
          }
        ]
      },
      {
        "final": true,
        "alternatives": [
          {
            "transcript": "she could have picked it up anywhere investigators agreed so they turn their attention to the linear marks found on Janice Stein the March were made by man made object they were clearly of a shape and appearance that would not be normally found in nature ",
            "confidence": 0.83
          }
        ]
      },
      {
        "final": true,
        "alternatives": [
          {
            "transcript": "while looking inside dog Mausers car detective Bob Smith 40 phone calls ",
            "confidence": 0.58
          }
        ]
      },
      {
        "final": true,
        "alternatives": [
          {
            "transcript": "here on the back of your neck stand up when you're gone this could be tomorrow one of the marks on the lake but he didn't tell anyone about his discovery instead he sent photographs of Janice skin marks to Gary Robertson pioneer in the field of photogrammetry to see what he thought might have cost them which wanted to identify the exact size of the March down to the micro millimeter so he scanned every autopsy photograph of the marks which enabled him to create a 3 dimensional model for extracting the measurements say from the left photograph extracting it from the right photographs in the computer software merges that into a 3 dimensional measurement or a model that we can extract and you later ",
            "confidence": 0.82
          }
        ]
      },
      {
        "final": true,
        "alternatives": [
          {
            "transcript": "judging from the size and shape Robertson suspected that at least one of the marks was caused by the top part of the seat belt buckles ",
            "confidence": 0.9
          }
        ]
      },
      {
        "final": true,
        "alternatives": [
          {
            "transcript": "this was precisely what Hans Bosma thought ",
            "confidence": 0.81
          }
        ]
      },
      {
        "final": true,
        "alternatives": [
          {
            "transcript": "but he wanted Robertson's independent analysis ",
            "confidence": 0.94
          }
        ]
      },
      {
        "final": true,
        "alternatives": [
          {
            "transcript": "well normally if I don't have any information so I wasn't aware of anything about the vehicle next Robertson flew to Modesto California to conduct an experiment in dog Mausers car he wanted to try to recreate the same skin pattern that was on genocide ",
            "confidence": 0.83
          }
        ]
      },
      {
        "final": true,
        "alternatives": [
          {
            "transcript": "he placed a live model the same height and weight as Jenna in the backseat of the vehicle over the rear seat belt buckle ",
            "confidence": 0.84
          }
        ]
      },
      {
        "final": true,
        "alternatives": [
          {
            "transcript": "it was a hatchback and one of the back seats was broken and was kept flat ",
            "confidence": 0.79
          }
        ]
      },
      {
        "final": true,
        "alternatives": [
          {
            "transcript": "the model remained in the same position for 15 minutes the time it would have taken to drive from Janice house to the dump site when the model was photographed Robertson and Bosma discovered what caused the other marks on Janice laying ",
            "confidence": 0.79
          }
        ]
      },
      {
        "final": true,
        "alternatives": [
          {
            "transcript": "when he placed her in there ",
            "confidence": 0.96
          }
        ]
      },
      {
        "final": true,
        "alternatives": [
          {
            "transcript": "the ",
            "confidence": 0.78
          }
        ]
      },
      {
        "final": true,
        "alternatives": [
          {
            "transcript": "there's carpet on the back of that at C. pack because it lays flat so you have a nice car ",
            "confidence": 0.71
          }
        ]
      },
      {
        "final": true,
        "alternatives": [
          {
            "transcript": "the carpet B. falls over as he pulls or pushes her over that particular hearing ",
            "confidence": 0.85
          }
        ]
      },
      {
        "final": true,
        "alternatives": [
          {
            "transcript": "and that carpet beat was what won the indentations were on on her late ",
            "confidence": 0.7
          }
        ]
      },
      {
        "final": true,
        "alternatives": [
          {
            "transcript": "just to make sure Robertson put the models pictures into his computer and compared them to the marks on Janice lag ",
            "confidence": 0.77
          }
        ]
      },
      {
        "final": true,
        "alternatives": [
          {
            "transcript": "it was a virtual match ",
            "confidence": 0.95
          }
        ]
      },
      {
        "final": true,
        "alternatives": [
          {
            "transcript": "the beating which would cause the imprint on the model and on the victim's late match precisely down to micron's ",
            "confidence": 0.76
          }
        ]
      },
      {
        "final": true,
        "alternatives": [
          {
            "transcript": "the way it ",
            "confidence": 0.3
          }
        ]
      },
      {
        "final": true,
        "alternatives": [
          {
            "transcript": "of the carpet ",
            "confidence": 0.88
          }
        ]
      },
      {
        "final": true,
        "alternatives": [
          {
            "transcript": "in the orientation that matched as well also the length matching interestingly the rip carpet in the backseat of dogs Kerr was unusual something you wouldn't find in other cars when he came back and said you know it's a match we were just a static we finally got a real nail this guy now we gotta because now we complete Jenin and car all the pieces fit together only one way and that's showing ",
            "confidence": 0.81
          }
        ]
      },
      {
        "final": true,
        "alternatives": [
          {
            "transcript": "the amounts are guilty of killing China ",
            "confidence": 0.59
          }
        ]
      },
      {
        "final": true,
        "alternatives": [
          {
            "transcript": "it is ",
            "confidence": 0.65
          }
        ]
      },
      {
        "final": true,
        "alternatives": [
          {
            "transcript": "choose me they didn't fear right ",
            "confidence": 0.52
          }
        ]
      },
      {
        "final": true,
        "alternatives": [
          {
            "transcript": "I'll say that on the screen and even saying in the court room they didn't have any theory other than the through the body children thrown over the side ",
            "confidence": 0.81
          }
        ]
      },
      {
        "final": true,
        "alternatives": [
          {
            "transcript": "and that she was in his car because of the mark on her leg that's all there was ",
            "confidence": 0.85
          }
        ]
      },
      {
        "final": true,
        "alternatives": [
          {
            "transcript": "based on the forensic botany and photogrammetry ",
            "confidence": 0.93
          }
        ]
      },
      {
        "final": true,
        "alternatives": [
          {
            "transcript": "Doug Moser was arrested and charged with this step daughters American ",
            "confidence": 0.7
          }
        ]
      },
      {
        "final": true,
        "alternatives": [
          {
            "transcript": "prosecutors wondered what motivated Doug Mauser killed his 14 year old step daughter Jenna how can you possibly imagine someone doing something so horrible ",
            "confidence": 0.89
          }
        ]
      },
      {
        "final": true,
        "alternatives": [
          {
            "transcript": "I can't imagine it but it happens unfortunately all the time ",
            "confidence": 0.95
          }
        ]
      },
      {
        "final": true,
        "alternatives": [
          {
            "transcript": "prosecutors found evidence that Jenna didn't always do what her parents asked ",
            "confidence": 0.9
          }
        ]
      },
      {
        "final": true,
        "alternatives": [
          {
            "transcript": "she saw counselor with some regularity she had oppositional defiant disorder that she was ",
            "confidence": 0.87
          }
        ]
      },
      {
        "final": true,
        "alternatives": [
          {
            "transcript": "the very defiant very aggressive very confrontational with family with parents the monsters telephone records provided a possible clue ",
            "confidence": 0.86
          }
        ]
      },
      {
        "final": true,
        "alternatives": [
          {
            "transcript": "yeah I just got back from the most any on the morning of her death ",
            "confidence": 0.77
          }
        ]
      },
      {
        "final": true,
        "alternatives": [
          {
            "transcript": "Janet was on the telephone violating her parents rules his name Scott really this year ",
            "confidence": 0.85
          }
        ]
      },
      {
        "final": true,
        "alternatives": [
          {
            "transcript": "prosecutors believe Doug cotton channel on the phone lost his temper he still struck ",
            "confidence": 0.7
          }
        ]
      },
      {
        "final": true,
        "alternatives": [
          {
            "transcript": "Jenna prosecutors believe dogs impulsive act of violence threatened his career he couldn't rest in allegation that he had hit her struck her he was working at Lawrence Livermore lab and his security clearance so any kind of a criminal conviction on his record would have been very difficult for him and put his job in jeopardy with general unconscious I'm not sure what to do ",
            "confidence": 0.84
          }
        ]
      },
      {
        "final": true,
        "alternatives": [
          {
            "transcript": "prosecutors think dog panicked and strangled her to death ",
            "confidence": 0.81
          }
        ]
      },
      {
        "final": true,
        "alternatives": [
          {
            "transcript": "if you remove Janice closing to eliminate possible trace evidence when Doug push Jenna's body into the backseat of his car he displaced the carpet the underside of the carpet and the seat belt buckle left signature marks on her skin that wouldn't disappear since there was no blood flow ",
            "confidence": 0.8
          }
        ]
      },
      {
        "final": true,
        "alternatives": [
          {
            "transcript": "Doug chose a dumpsite 15 minutes away pulled his car off the road which picked up the best of starts this ",
            "confidence": 0.7
          }
        ]
      },
      {
        "final": true,
        "alternatives": [
          {
            "transcript": "the same stage of development ",
            "confidence": 0.98
          }
        ]
      },
      {
        "final": true,
        "alternatives": [
          {
            "transcript": "found on Jenna's body ",
            "confidence": 0.45
          }
        ]
      },
      {
        "final": true,
        "alternatives": [
          {
            "transcript": "prosecutors think dogs simply got lucky when the security cameras at both his office and the fast food restaurant we're working ",
            "confidence": 0.81
          }
        ]
      },
      {
        "final": true,
        "alternatives": [
          {
            "transcript": "zdummyz.made a crucial mistake during his interrogation he said he used his computer that Saturday at the ",
            "confidence": 0.91
          }
        ]
      },
      {
        "final": true,
        "alternatives": [
          {
            "transcript": "but his employer found no evidence that dog log in ",
            "confidence": 0.79
          }
        ]
      },
      {
        "final": true,
        "alternatives": [
          {
            "transcript": "they couldn't find any evidence whatsoever that he had done to his computers when he said he did basically we caught up with continental line ",
            "confidence": 0.83
          }
        ]
      },
      {
        "final": true,
        "alternatives": [
          {
            "transcript": "Doug Mauser was tried and convicted of second degree murder and sentenced to 15 years to life in prison ",
            "confidence": 0.94
          }
        ]
      },
      {
        "final": true,
        "alternatives": [
          {
            "transcript": "he continues to maintain his innocence ",
            "confidence": 0.98
          }
        ]
      },
      {
        "final": true,
        "alternatives": [
          {
            "transcript": "I used for me this is the greatest failure of my life ",
            "confidence": 0.87
          }
        ]
      },
      {
        "final": true,
        "alternatives": [
          {
            "transcript": "the only way I live with the situation is that I did ",
            "confidence": 0.94
          }
        ]
      },
      {
        "final": true,
        "alternatives": [
          {
            "transcript": "the best ",
            "confidence": 0.96
          }
        ]
      },
      {
        "final": true,
        "alternatives": [
          {
            "transcript": "that I could I did everything that I could think possible ",
            "confidence": 0.93
          }
        ]
      },
      {
        "final": true,
        "alternatives": [
          {
            "transcript": "definitely Jekyll and Hyde personality there one moment he's he's Mr calm and cool and next moment here's something totally different ",
            "confidence": 0.83
          }
        ]
      },
      {
        "final": true,
        "alternatives": [
          {
            "transcript": "I think she really really happy to know that that people love her so much to to fight to find the real answers to really what happened to her ",
            "confidence": 0.9
          }
        ]
      },
      {
        "final": true,
        "alternatives": [
          {
            "transcript": "and she would be happy to know that we haven't forgotten about her ",
            "confidence": 1
          }
        ]
      },
      {
        "final": true,
        "alternatives": [
          {
            "transcript": "the case against Mauser was largely circumstantial ",
            "confidence": 0.91
          }
        ]
      },
      {
        "final": true,
        "alternatives": [
          {
            "transcript": "but the photogrammetry helped convince the jury ",
            "confidence": 0.8
          }
        ]
      },
      {
        "final": true,
        "alternatives": [
          {
            "transcript": "photogrammetry was the key element and it was used to solve the case and without photogrammetry this case we would have gone unsolved ",
            "confidence": 0.84
          }
        ]
      }
    ],
    "result_index": 0
  }
]